fancy_permissions/__init__.py
drf_fancy_permissions-1.0.0.dist-info/METADATA
drf_fancy_permissions-1.0.0.dist-info/WHEEL
drf_fancy_permissions-1.0.0.dist-info/top_level.txt
drf_fancy_permissions-1.0.0.dist-info/RECORD
