Metadata-Version: 2.1
Name: drf-fancy-permissions
Version: 1.0.0
Summary: Utilities for defining fine-grained permissions in the Django Rest Framework based API views
Author: IIIT
Author-email: github@iiit.pl
License: UNKNOWN
Platform: UNKNOWN
Classifier: Environment :: Web Environment
Classifier: Framework :: Django
Classifier: Intended Audience :: Developers
Classifier: Operating System :: OS Independent
Classifier: Programming Language :: Python
Classifier: Programming Language :: Python :: 3.6
Classifier: Programming Language :: Python :: 3.7
Classifier: Programming Language :: Python :: 3.8
Classifier: Programming Language :: Python :: 3.9
Requires-Dist: Django (<3.0,>=1.10)
Requires-Dist: djangorestframework (>=3.3.2)
